README.rst
setup.py
angus/__init__.py
angus/analytics.py
angus/framework.py
angus/jobs.py
angus/service.py
angus/storage.py
angus/streams.py
angus_framework.egg-info/PKG-INFO
angus_framework.egg-info/SOURCES.txt
angus_framework.egg-info/dependency_links.txt
angus_framework.egg-info/requires.txt
angus_framework.egg-info/top_level.txt