Metadata-Version: 1.0
Name: angus-framework
Version: 0.1.0
Summary: Angus Cloud Framework
Home-page: http://www.angus.ai/
Author: Aurélien Moreau
Author-email: aurelien.moreau@angus.ai
License: UNKNOWN
Platform: UNKNOWN
